setup.cfg
setup.py
vins.egg-info/PKG-INFO
vins.egg-info/SOURCES.txt
vins.egg-info/dependency_links.txt
vins.egg-info/entry_points.txt
vins.egg-info/requires.txt
vins.egg-info/top_level.txt
vins_cli/__init__.py
vins_cli/client.py
vins_cli/default.py
vins_cli/deploy.py
vins_cli/exceptions.py
vins_cli/init.py
vins_cli/settings.py
vins_cli/intent/__init__.py
vins_cli/intent/add.py