Metadata-Version: 1.0
Name: vins
Version: 1.0.11.0
Summary: Voice INterfaces Service CLI
Home-page: UNKNOWN
Author: Evgeny Volkov
Author-email: wolf510@inbox.ru
License: UNKNOWN
Platform: UNKNOWN
